.DS_Store
oocsi/__init__.py
oocsi-0.4.3.dist-info/LICENSE
oocsi-0.4.3.dist-info/METADATA
oocsi-0.4.3.dist-info/WHEEL
oocsi-0.4.3.dist-info/top_level.txt
oocsi-0.4.3.dist-info/RECORD
