Metadata-Version: 2.1
Name: oocsi
Version: 0.4.3
Summary: Python Client for OOCSI
Home-page: https://github.com/iddi/oocsi-python
Author: matsfunk
Author-email: m.funk@tue.nl
License: MIT
Platform: UNKNOWN
License-File: LICENSE
